MANIFEST.in
README.rst
setup.py
stdeb.cfg
xfs.c
xfs.pyx
xfs.egg-info/PKG-INFO
xfs.egg-info/SOURCES.txt
xfs.egg-info/dependency_links.txt
xfs.egg-info/top_level.txt