Metadata-Version: 1.1
Name: xfs
Version: 0.3
Summary: XFS filesystem API
Home-page: https://github.com/redbo/python-xfs
Author: Michael Barton
Author-email: mike@weirdlooking.com
License: UNKNOWN
Platform: UNKNOWN
Classifier: Development Status :: 4 - Beta
Classifier: Environment :: Console
Classifier: Intended Audience :: Developers
Classifier: Intended Audience :: Information Technology
Classifier: Operating System :: OS Independent
Classifier: Programming Language :: Python :: 2.6
Classifier: Programming Language :: Python :: 2.7
Classifier: Environment :: No Input/Output (Daemon)
